{
  "project_info": {
    "project_number": "951987309428",
    "firebase_url": "https://androidapp-293f6.firebaseio.com",
    "project_id": "androidapp-293f6",
    "storage_bucket": "androidapp-293f6.appspot.com"
  },
  "client": [
    {
      "client_info": {
        "mobilesdk_app_id": "1:951987309428:android:59441d4c3a985ed529ba21",
        "android_client_info": {
          "package_name": "com.example.newsapp"
        }
      },
      "oauth_client": [
        {
          "client_id": "951987309428-9h2526rl8huc0akkaugjgvs3l5dn6992.apps.googleusercontent.com",
          "client_type": 3
        }
      ],
      "api_key": [
        {
          "current_key": "AIzaSyBJvFfD92G1hXyZYrgXisjnGrJm-enetLA"
        }
      ],
      "services": {
        "appinvite_service": {
          "other_platform_oauth_client": [
            {
              "client_id": "951987309428-9h2526rl8huc0akkaugjgvs3l5dn6992.apps.googleusercontent.com",
              "client_type": 3
            }
          ]
        }
      }
    }
  ],
  "configuration_version": "1"
}